docs/Makefile
docs/api_reference.rst
docs/classes.rst
docs/conf.py
docs/fit.rst
docs/index.rst
docs/make.bat
docs/quickstart.rst
docs/_static/concept.png
docs/_static/forest_mask_bolivia.png
docs/_static/iqr_results_bolivia.png
docs/_static/logo.png
docs/gallery/README.rst
docs/gallery/dontplot_bolivia_stac.py
docs/gallery/plot_parallel_computing.py
docs/gallery/plot_simulation_data.py
nrt/__init__.py
nrt/fit_methods.py
nrt/log.py
nrt/outliers.py
nrt/stats.py
nrt/utils.py
nrt/utils_efp.py
nrt/monitor/__init__.py
nrt/monitor/ccdc.py
nrt/monitor/cusum.py
nrt/monitor/ewma.py
nrt/monitor/iqr.py
nrt/monitor/mosum.py
tests/integration_tests/__init__.py
tests/integration_tests/conftest.py
tests/integration_tests/test_ccdc.py
tests/integration_tests/test_monitor.py
tests/unit_tests/conftest.py
tests/unit_tests/test_fit_methods.py
tests/unit_tests/test_outliers.py
tests/unit_tests/test_stats.py
tests/unit_tests/test_utils_efp.py
tests/unit_tests/data/RLM_X.csv
tests/unit_tests/data/RLM_y.csv
tests/unit_tests/data/X.csv
tests/unit_tests/data/cusum_result.csv
tests/unit_tests/data/dates.csv
tests/unit_tests/data/efp_result.csv
tests/unit_tests/data/mosum_result.csv
tests/unit_tests/data/roc_history_result.csv
tests/unit_tests/data/rr_result.csv
tests/unit_tests/data/y.csv
nrt-0.3.0.dist-info/LICENSE
nrt-0.3.0.dist-info/METADATA
nrt-0.3.0.dist-info/WHEEL
nrt-0.3.0.dist-info/top_level.txt
nrt-0.3.0.dist-info/RECORD
