Metadata-Version: 2.1
Name: nrt
Version: 0.3.0
Summary: Online monitoring with xarray
Author: Jonas Viehweger, Chris Holden
Author-email: Loic Dutrieux <loic.dutrieux@ec.europa.eu>
License: EUPL-1.2
Project-URL: Homepage, https://github.com/ec-jrc/nrt.git
Keywords: sentinel2,xarray,datacube,monitoring,change
Classifier: Programming Language :: Python :: 3
Classifier: Programming Language :: Python :: 3.9
Classifier: Programming Language :: Python :: 3.10
Classifier: Programming Language :: Python :: 3.11
Classifier: Programming Language :: Python :: 3.12
Classifier: License :: OSI Approved :: European Union Public Licence 1.2 (EUPL 1.2)
Requires-Python: >=3.9
License-File: LICENSE
Requires-Dist: numpy
Requires-Dist: scipy
Requires-Dist: xarray
Requires-Dist: rasterio
Requires-Dist: netCDF4
Requires-Dist: numba!=0.59.*
Requires-Dist: pandas
Requires-Dist: affine
Requires-Dist: nrt-data
Provides-Extra: docs
Requires-Dist: sphinx==7.4.7; extra == "docs"
Requires-Dist: dask; extra == "docs"
Requires-Dist: sphinx-rtd-theme==2.0.0; extra == "docs"
Requires-Dist: matplotlib==3.9.1; extra == "docs"
Requires-Dist: sphinx-gallery==0.17.0; extra == "docs"
Provides-Extra: tests
Requires-Dist: pytest; extra == "tests"
